iytdl/__init__.py
iytdl/constants.py
iytdl/downloader.py
iytdl/exceptions.py
iytdl/extractors.py
iytdl/formatter.py
iytdl/main.py
iytdl/processes.py
iytdl/sql_cache.py
iytdl/types/__init__.py
iytdl/types/external_downloader.py
iytdl/types/results.py
iytdl/upload_lib/__init__.py
iytdl/upload_lib/ext.py
iytdl/upload_lib/functions.py
iytdl/upload_lib/progress.py
iytdl/upload_lib/uploader.py
iytdl/utils.py
iytdl-0.5.5.dist-info/LICENSE
iytdl-0.5.5.dist-info/WHEEL
iytdl-0.5.5.dist-info/METADATA
iytdl-0.5.5.dist-info/RECORD
